chanmqttsproxy/__init__.py
chanmqttsproxy/channelsmqttproxy.py
chanmqttsproxy/mqttconsumer.py
chanmqttsproxy-0.1.dist-info/LICENSE
chanmqttsproxy-0.1.dist-info/METADATA
chanmqttsproxy-0.1.dist-info/WHEEL
chanmqttsproxy-0.1.dist-info/top_level.txt
chanmqttsproxy-0.1.dist-info/RECORD
